aetcd/__init__.py
aetcd/client.py
aetcd/exceptions.py
aetcd/leases.py
aetcd/locks.py
aetcd/members.py
aetcd/rtypes.py
aetcd/transactions.py
aetcd/utils.py
aetcd/watcher.py
aetcd/rpc/__init__.py
aetcd/rpc/auth_pb2.py
aetcd/rpc/auth_pb2_grpc.py
aetcd/rpc/kv_pb2.py
aetcd/rpc/kv_pb2_grpc.py
aetcd/rpc/rpc_pb2.py
aetcd/rpc/rpc_pb2_grpc.py
aetcd-1.0.0a4.dist-info/LICENSE
aetcd-1.0.0a4.dist-info/METADATA
aetcd-1.0.0a4.dist-info/WHEEL
aetcd-1.0.0a4.dist-info/top_level.txt
aetcd-1.0.0a4.dist-info/RECORD
