Metadata-Version: 2.1
Name: aetcd
Version: 1.0.0a4
Summary: Python asyncio-based client for etcd
Home-page: https://github.com/martyanov/aetcd
Author: Andrey Martyanov
Author-email: andrey@martyanov.com
License: Apache Software License 2.0
Project-URL: Documentation, https://aetcd.readthedocs.io
Project-URL: Code, https://github.com/martyanov/aetcd
Project-URL: Issues, https://github.com/martyanov/aetcd/issues
Keywords: etcd3
Classifier: Development Status :: 3 - Alpha
Classifier: Intended Audience :: Developers
Classifier: License :: OSI Approved :: Apache Software License
Classifier: Programming Language :: Python :: 3
Classifier: Programming Language :: Python :: 3.8
Classifier: Programming Language :: Python :: 3.9
Classifier: Programming Language :: Python :: 3.10
Classifier: Programming Language :: Python :: 3.11
Requires-Python: >=3.8,<4.0
License-File: LICENSE
Requires-Dist: grpcio (<2,>1.51)
Requires-Dist: protobuf (<5,>4)
Provides-Extra: dev
Requires-Dist: flake8-commas (==2.1.0) ; extra == 'dev'
Requires-Dist: flake8-docstrings (==1.7.0) ; extra == 'dev'
Requires-Dist: flake8-isort (==6.0.0) ; extra == 'dev'
Requires-Dist: flake8-quotes (==3.3.2) ; extra == 'dev'
Requires-Dist: flake8 (==6.0.0) ; extra == 'dev'
Requires-Dist: grpcio-tools (==1.51.1) ; extra == 'dev'
Requires-Dist: pep8-naming (==0.13.3) ; extra == 'dev'
Requires-Dist: twine (==4.0.2) ; extra == 'dev'
Provides-Extra: doc
Requires-Dist: sphinx (==6.1.3) ; extra == 'doc'
Requires-Dist: sphinx-rtd-theme (==1.2.0) ; extra == 'doc'
Provides-Extra: test
Requires-Dist: pytest-asyncio (==0.20.3) ; extra == 'test'
Requires-Dist: pytest-cov (==4.0.0) ; extra == 'test'
Requires-Dist: pytest-mock (==3.10.0) ; extra == 'test'
Requires-Dist: pytest (==7.2.1) ; extra == 'test'
